itscalledsoccer/__init__.py
itscalledsoccer/client.py
itscalledsoccer-1.3.3.dist-info/licenses/LICENSE
itscalledsoccer-1.3.3.dist-info/METADATA
itscalledsoccer-1.3.3.dist-info/WHEEL
itscalledsoccer-1.3.3.dist-info/top_level.txt
itscalledsoccer-1.3.3.dist-info/RECORD
