Metadata-Version: 2.4
Name: itscalledsoccer
Version: 1.3.3
Summary: Programmatically interact with the American Soccer Analysis API
Author-email: American Soccer Analysis <americansocceranalysis@gmail.com>
License: MIT
Project-URL: Repository, https://github.com/American-Soccer-Analysis/itscalledsoccer
Keywords: stats,soccer,api,football,american,machine learning
Classifier: Programming Language :: Python
Classifier: Programming Language :: Python :: 3
Classifier: Programming Language :: Python :: 3.9
Classifier: Programming Language :: Python :: 3.10
Classifier: Programming Language :: Python :: 3.11
Classifier: Programming Language :: Python :: 3.12
Requires-Python: >=3.9
License-File: LICENSE
Requires-Dist: requests>=2.31.0
Requires-Dist: CacheControl>=0.13.1
Requires-Dist: rapidfuzz>=3.2.0
Requires-Dist: pandas>=2.1.0
Dynamic: license-file
